{"admin": {"created": {"date": "2018-11-14", "schema_version": "1.0"}, "last_modified": {"date": "2024-12-11", "schema_version": "2.1"}}, "domains": [], "established": 1998, "external_ids": [{"all": ["grid.460347.2"], "preferred": "grid.460347.2", "type": "grid"}], "id": "https://ror.org/03n3nz506", "links": [{"type": "website", "value": "http://careers.gm.com/"}], "locations": [{"geonames_details": {"continent_code": "EU", "continent_name": "Europe", "country_code": "PL", "country_name": "Poland", "country_subdivision_code": "24", "country_subdivision_name": "Silesia", "lat": 50.29761, "lng": 18.67658, "name": "Gliwice"}, "geonames_id": 3099230}], "names": [{"lang": null, "types": ["ror_display", "label"], "value": "General Motors (Poland)"}], "relationships": [{"label": "General Motors (United States)", "type": "parent", "id": "https://ror.org/05addee68"}], "status": "active", "types": ["company"]}