{"admin": {"created": {"date": "2018-11-14", "schema_version": "1.0"}, "last_modified": {"date": "2024-12-11", "schema_version": "2.1"}}, "domains": [], "established": 2000, "external_ids": [{"all": ["grid.456035.1"], "preferred": "grid.456035.1", "type": "grid"}], "id": "https://ror.org/0019se992", "links": [{"type": "website", "value": "http://www.princetonlightwave.com/"}], "locations": [{"geonames_details": {"continent_code": "NA", "continent_name": "North America", "country_code": "US", "country_name": "United States", "country_subdivision_code": "NJ", "country_subdivision_name": "New Jersey", "lat": 40.31622, "lng": -74.51376, "name": "Cranbury"}, "geonames_id": 5097006}], "names": [{"lang": null, "types": ["acronym"], "value": "PLI"}, {"lang": null, "types": ["ror_display", "label"], "value": "Princeton Lightwave (United States)"}], "relationships": [], "status": "active", "types": ["company"]}