{"admin": {"created": {"date": "2018-11-14", "schema_version": "1.0"}, "last_modified": {"date": "2024-12-11", "schema_version": "2.1"}}, "domains": [], "established": 1931, "external_ids": [{"all": ["grid.459143.e"], "preferred": "grid.459143.e", "type": "grid"}, {"all": ["Q30338383"], "preferred": null, "type": "wikidata"}], "id": "https://ror.org/04q4re318", "links": [{"type": "website", "value": "http://www.cgg.com/en"}, {"type": "wikipedia", "value": "https://en.wikipedia.org/wiki/CGG_(company)"}], "locations": [{"geonames_details": {"continent_code": "EU", "continent_name": "Europe", "country_code": "NO", "country_name": "Norway", "country_subdivision_code": "03", "country_subdivision_name": "Oslo", "lat": 59.91273, "lng": 10.74609, "name": "Oslo"}, "geonames_id": 3143244}], "names": [{"lang": null, "types": ["alias"], "value": "Compagnie G\u00e9n\u00e9rale de G\u00e9ophysique"}, {"lang": null, "types": ["ror_display", "label"], "value": "GGG (Norway)"}], "relationships": [{"label": "GGG (France)", "type": "parent", "id": "https://ror.org/03end3932"}], "status": "active", "types": ["company"]}