{"admin": {"created": {"date": "2019-02-17", "schema_version": "1.0"}, "last_modified": {"date": "2024-12-11", "schema_version": "2.1"}}, "domains": [], "established": 2009, "external_ids": [{"all": ["grid.503115.3"], "preferred": "grid.503115.3", "type": "grid"}, {"all": ["0000 0004 7780 8489"], "preferred": "0000 0004 7780 8489", "type": "isni"}, {"all": ["Q51783166"], "preferred": null, "type": "wikidata"}], "id": "https://ror.org/05jw85995", "links": [{"type": "website", "value": "http://www.cnrt.ensicaen.fr/"}], "locations": [{"geonames_details": {"continent_code": "EU", "continent_name": "Europe", "country_code": "FR", "country_name": "France", "country_subdivision_code": "NOR", "country_subdivision_name": "Normandy", "lat": 49.18585, "lng": -0.35912, "name": "Caen"}, "geonames_id": 3029241}], "names": [{"lang": "fr", "types": ["ror_display", "label"], "value": "CNRT Mat\u00e9riaux"}, {"lang": "fr", "types": ["label"], "value": "Centre National de Recherche Technologique"}], "relationships": [{"label": "Institut de Chimie", "type": "parent", "id": "https://ror.org/02cte4b68"}, {"label": "Universit\u00e9 Le Havre Normandie", "type": "parent", "id": "https://ror.org/05v509s40"}, {"label": "Universit\u00e9 de Caen Normandie", "type": "parent", "id": "https://ror.org/051kpcy16"}, {"label": "\u00c9cole Nationale Sup\u00e9rieure d'Ing\u00e9nieurs de Caen", "type": "parent", "id": "https://ror.org/01fpqqe90"}], "status": "active", "types": ["facility"]}