{"admin": {"created": {"date": "2018-11-14", "schema_version": "1.0"}, "last_modified": {"date": "2024-12-11", "schema_version": "2.1"}}, "domains": [], "established": 1965, "external_ids": [{"all": ["grid.472416.2"], "preferred": "grid.472416.2", "type": "grid"}, {"all": ["0000 0004 0525 5272"], "preferred": null, "type": "isni"}, {"all": ["Q7894082"], "preferred": null, "type": "wikidata"}], "id": "https://ror.org/019njds38", "links": [{"type": "website", "value": "http://www.uti.edu//"}, {"type": "wikipedia", "value": "https://en.wikipedia.org/wiki/Universal_Technical_Institute"}], "locations": [{"geonames_details": {"continent_code": "NA", "continent_name": "North America", "country_code": "US", "country_name": "United States", "country_subdivision_code": "AZ", "country_subdivision_name": "Arizona", "lat": 33.50921, "lng": -111.89903, "name": "Scottsdale"}, "geonames_id": 5313457}], "names": [{"lang": null, "types": ["acronym"], "value": "UTI"}, {"lang": "en", "types": ["ror_display", "label"], "value": "Universal Technical Institute"}], "relationships": [{"label": "Universal Technical Institute Dallas-Fort Worth", "type": "child", "id": "https://ror.org/00f6qhc93"}, {"label": "Universal Technical Institute of Illinois", "type": "child", "id": "https://ror.org/02evj4e11"}], "status": "active", "types": ["education"]}