{"admin": {"created": {"date": "2018-11-14", "schema_version": "1.0"}, "last_modified": {"date": "2024-12-11", "schema_version": "2.1"}}, "domains": [], "established": 1896, "external_ids": [{"all": ["grid.485975.2"], "preferred": "grid.485975.2", "type": "grid"}], "id": "https://ror.org/051hq3021", "links": [{"type": "website", "value": "https://www.ctscorp.com/"}], "locations": [{"geonames_details": {"continent_code": "EU", "continent_name": "Europe", "country_code": "CZ", "country_name": "Czechia", "country_subdivision_code": "80", "country_subdivision_name": "Moravskoslezsk\u00fd", "lat": 49.83465, "lng": 18.28204, "name": "Ostrava"}, "geonames_id": 3068799}], "names": [{"lang": null, "types": ["ror_display", "label"], "value": "CTS Corporation (Czechia)"}], "relationships": [{"label": "CTS Corporation (United States)", "type": "parent", "id": "https://ror.org/015r6y659"}], "status": "active", "types": ["company"]}